[
    {
        "home_team": "Brampton Steelheads",
        "away_team": "Peterborough Petes",
        "winner": "Brampton Steelheads",
        "odds": {
            "Brampton Steelheads": "-676",
            "Peterborough Petes": "+451"
        },
        "game_time": "7:00 pm"
    },
    {
        "home_team": "Kingston Frontenacs",
        "away_team": "Brantford Bulldogs",
        "winner": "Kingston Frontenacs",
        "odds": {
            "Kingston Frontenacs": "-132",
            "Brantford Bulldogs": "+106"
        },
        "game_time": "7:00 pm"
    },
    {
        "home_team": "Kitchener Rangers",
        "away_team": "Owen Sound Attack",
        "winner": "Kitchener Rangers",
        "odds": {
            "Kitchener Rangers": "-247",
            "Owen Sound Attack": "+194"
        },
        "game_time": "7:00 pm"
    },
    {
        "home_team": "London Knights",
        "away_team": "Windsor Spitfires",
        "winner": "London Knights",
        "odds": {
            "London Knights": "-119",
            "Windsor Spitfires": "-103"
        },
        "game_time": "7:00 pm"
    },
    {
        "home_team": "Niagara IceDogs",
        "away_team": "North Bay Battalion",
        "winner": "Niagara IceDogs",
        "odds": {
            "Niagara IceDogs": "-233",
            "North Bay Battalion": "+183"
        },
        "game_time": "7:00 pm"
    },
    {
        "home_team": "Sarnia Sting",
        "away_team": "Flint Firebirds",
        "winner": "Flint Firebirds",
        "odds": {
            "Sarnia Sting": "+146",
            "Flint Firebirds": "-182"
        },
        "game_time": "7:05 pm"
    },
    {
        "home_team": "Sudbury Wolves",
        "away_team": "Oshawa Generals",
        "winner": "Oshawa Generals",
        "odds": {
            "Sudbury Wolves": "+110",
            "Oshawa Generals": "-136"
        },
        "game_time": "7:05 pm"
    },
    {
        "home_team": "Soo Greyhounds",
        "away_team": "Saginaw Spirit",
        "winner": "Saginaw Spirit",
        "odds": {
            "Soo Greyhounds": "+162",
            "Saginaw Spirit": "-204"
        },
        "game_time": "7:07 pm"
    }
]