[
    {
        "home_team": "Brantford Bulldogs",
        "away_team": "Sudbury Wolves",
        "winner": "Brantford Bulldogs",
        "odds": {
            "Brantford Bulldogs": "-145",
            "Sudbury Wolves": "+117"
        },
        "game_time": "7:00 pm"
    },
    {
        "home_team": "Ottawa 67's",
        "away_team": "Oshawa Generals",
        "winner": "Oshawa Generals",
        "odds": {
            "Ottawa 67's": "+246",
            "Oshawa Generals": "-323"
        },
        "game_time": "7:00 pm"
    },
    {
        "home_team": "Windsor Spitfires",
        "away_team": "Saginaw Spirit",
        "winner": "Windsor Spitfires",
        "odds": {
            "Windsor Spitfires": "-130",
            "Saginaw Spirit": "+105"
        },
        "game_time": "7:05 pm"
    }
]