[
    {
        "home_team": "North Bay Battalion",
        "away_team": "Soo Greyhounds",
        "winner": "Soo Greyhounds",
        "odds": {
            "North Bay Battalion": "+173",
            "Soo Greyhounds": "-219"
        },
        "game_time": "7:00 pm"
    },
    {
        "home_team": "Peterborough Petes",
        "away_team": "Flint Firebirds",
        "winner": "Flint Firebirds",
        "odds": {
            "Peterborough Petes": "+278",
            "Flint Firebirds": "-372"
        },
        "game_time": "7:05 pm"
    }
]