[
    {
        "date": "2025-01-30",
        "home_team": "Saginaw Spirit",
        "away_team": "Kingston Frontenacs",
        "predicted_winner": "Kingston Frontenacs",
        "actual_winner": "Kingston Frontenacs",
        "home_score": 5,
        "away_score": 9,
        "odds": {
            "Saginaw Spirit": "-106",
            "Kingston Frontenacs": "-116"
        }
    },
    {
        "date": "2025-02-01",
        "home_team": "Barrie Colts",
        "away_team": "Niagara IceDogs",
        "predicted_winner": "Barrie Colts",
        "actual_winner": "Barrie Colts",
        "home_score": 7,
        "away_score": 6,
        "odds": {
            "Barrie Colts": "-123",
            "Niagara IceDogs": "-100"
        }
    },
    {
        "date": "2025-02-02",
        "home_team": "Windsor Spitfires",
        "away_team": "London Knights",
        "predicted_winner": "London Knights",
        "actual_winner": "Windsor Spitfires",
        "home_score": 4,
        "away_score": 3,
        "odds": {
            "Windsor Spitfires": "-101",
            "London Knights": "-122"
        }
    },
    {
        "date": "2025-02-05",
        "home_team": "Windsor Spitfires",
        "away_team": "Saginaw Spirit",
        "predicted_winner": "Windsor Spitfires",
        "actual_winner": "Saginaw Spirit",
        "home_score": 3,
        "away_score": 6,
        "odds": {
            "Windsor Spitfires": "-118",
            "Saginaw Spirit": "-104"
        }
    },
    {
        "date": "2025-02-07",
        "home_team": "Niagara IceDogs",
        "away_team": "Sudbury Wolves",
        "predicted_winner": "Niagara IceDogs",
        "actual_winner": "Sudbury Wolves",
        "home_score": 3,
        "away_score": 7,
        "odds": {
            "Niagara IceDogs": "-119",
            "Sudbury Wolves": "-104"
        }
    },
    {
        "date": "2025-02-08",
        "home_team": "Erie Otters",
        "away_team": "Sudbury Wolves",
        "predicted_winner": "Erie Otters",
        "actual_winner": "Erie Otters",
        "home_score": 7,
        "away_score": 4,
        "odds": {
            "Erie Otters": "-112",
            "Sudbury Wolves": "-110"
        }
    },
    {
        "date": "2025-02-11",
        "home_team": "Kitchener Rangers",
        "away_team": "Oshawa Generals",
        "predicted_winner": "Oshawa Generals",
        "actual_winner": "Oshawa Generals",
        "home_score": 3,
        "away_score": 4,
        "odds": {
            "Kitchener Rangers": "-102",
            "Oshawa Generals": "-121"
        }
    },
    {
        "date": "2025-02-12",
        "home_team": "Erie Otters",
        "away_team": "Niagara IceDogs",
        "predicted_winner": "Niagara IceDogs",
        "actual_winner": "Erie Otters",
        "home_score": 2,
        "away_score": 1,
        "odds": {
            "Erie Otters": "-105",
            "Niagara IceDogs": "-118"
        }
    },
    {
        "date": "2025-02-14",
        "home_team": "Flint Firebirds",
        "away_team": "Sudbury Wolves",
        "predicted_winner": "Sudbury Wolves",
        "actual_winner": "Sudbury Wolves",
        "home_score": 2,
        "away_score": 3,
        "odds": {
            "Flint Firebirds": "-102",
            "Sudbury Wolves": "-121"
        }
    },
    {
        "date": "2025-02-14",
        "home_team": "Saginaw Spirit",
        "away_team": "Windsor Spitfires",
        "predicted_winner": "Windsor Spitfires",
        "actual_winner": "Saginaw Spirit",
        "home_score": 3,
        "away_score": 2,
        "odds": {
            "Saginaw Spirit": "-104",
            "Windsor Spitfires": "-118"
        }
    },
    {
        "date": "2025-02-15",
        "home_team": "Oshawa Generals",
        "away_team": "Brampton Steelheads",
        "predicted_winner": "Brampton Steelheads",
        "actual_winner": "Brampton Steelheads",
        "home_score": 2,
        "away_score": 4,
        "odds": {
            "Oshawa Generals": "-105",
            "Brampton Steelheads": "-118"
        }
    }
]